src/__init__.py
src/categorical.py
src/data_description.py
src/data_input.py
src/download.py
src/feature_scaling.py
src/imputation.py
src/main.py
ml_preprocessor_cli-0.1.0.dist-info/LICENSE
ml_preprocessor_cli-0.1.0.dist-info/METADATA
ml_preprocessor_cli-0.1.0.dist-info/WHEEL
ml_preprocessor_cli-0.1.0.dist-info/entry_points.txt
ml_preprocessor_cli-0.1.0.dist-info/top_level.txt
ml_preprocessor_cli-0.1.0.dist-info/RECORD
