Metadata-Version: 2.2
Name: ml-preprocessor-cli
Version: 0.1.0
Summary: A CLI-based Machine Learning Data Preprocessor
Home-page: https://github.com/Surajnahak48/ml-preprocessor-cli
Author: Your Name
Author-email: your_email@example.com
Classifier: Programming Language :: Python :: 3
Classifier: License :: OSI Approved :: MIT License
Classifier: Operating System :: OS Independent
Requires-Python: >=3.7
License-File: LICENSE
Requires-Dist: pandas
Requires-Dist: scikit-learn
Dynamic: author
Dynamic: author-email
Dynamic: classifier
Dynamic: description
Dynamic: description-content-type
Dynamic: home-page
Dynamic: requires-dist
Dynamic: requires-python
Dynamic: summary
